test/__init__.py
test/test_etl.py
timeseries_etl/__init__.py
timeseries_etl/network_service.py
timeseries_etl/timeseries_etl.py
timeseries_etl-0.0.10.dist-info/LICENSE
timeseries_etl-0.0.10.dist-info/METADATA
timeseries_etl-0.0.10.dist-info/WHEEL
timeseries_etl-0.0.10.dist-info/top_level.txt
timeseries_etl-0.0.10.dist-info/RECORD
