Metadata-Version: 2.1
Name: timeseries-etl
Version: 0.0.10
Summary: A series of utils to extract timeseries data from a DB
Home-page: https://gde.kapschtraffic.com/brandon/timeseries-etl
Author: Alvaro Brandon
Author-email: alvaro.brandon@kapsch.net
License: UNKNOWN
Platform: UNKNOWN
Classifier: Programming Language :: Python :: 3
Classifier: License :: OSI Approved :: MIT License
Classifier: Operating System :: OS Independent
